pulumi_slack/__init__.py
pulumi_slack/_utilities.py
pulumi_slack/conversation.py
pulumi_slack/get_conversation.py
pulumi_slack/get_user.py
pulumi_slack/get_usergroup.py
pulumi_slack/provider.py
pulumi_slack/pulumi-plugin.json
pulumi_slack/py.typed
pulumi_slack/usergroup.py
pulumi_slack/config/__init__.py
pulumi_slack/config/__init__.pyi
pulumi_slack/config/vars.py
pulumi_slack-0.4.15.dist-info/METADATA
pulumi_slack-0.4.15.dist-info/WHEEL
pulumi_slack-0.4.15.dist-info/top_level.txt
pulumi_slack-0.4.15.dist-info/RECORD
